pictureTextCrop/__init__.py
pictureTextCrop/pictureTextCrop.py
pictureTextCrop/docs/__init__.py
pictureTextCrop/docs/help/About.html
pictureTextCrop/docs/help/Admin.html
pictureTextCrop/docs/help/Files.html
pictureTextCrop/docs/help/QuickStart.html
pictureTextCrop/docs/help/Run.html
pictureTextCrop/docs/help/View.html
pictureTextCrop/docs/help/__init__.py
pictureTextCrop/license/GNU Lesser General Public License - Wikipedia.pdf
pictureTextCrop/model/Configuration.py
pictureTextCrop/model/DbInterface.py
pictureTextCrop/model/Exif.py
pictureTextCrop/model/Folders.py
pictureTextCrop/model/HelpContent.py
pictureTextCrop/model/Installation.py
pictureTextCrop/model/Jobs.py
pictureTextCrop/model/__init__.py
pictureTextCrop/service/Extraction.py
pictureTextCrop/service/__init__.py
pictureTextCrop/view/Components.py
pictureTextCrop/view/Help.py
pictureTextCrop/view/Images.py
pictureTextCrop/view/QtAppComponents.py
pictureTextCrop/view/__init__.py
pictureTextCrop/view/icons/address-book.png
pictureTextCrop/view/icons/arrow-circle-135-left.png
pictureTextCrop/view/icons/arrow.png
pictureTextCrop/view/icons/asterisk.png
pictureTextCrop/view/icons/control-double.png
pictureTextCrop/view/icons/control-power.png
pictureTextCrop/view/icons/edit-list-order.png
pictureTextCrop/view/icons/folder--arrow.png
pictureTextCrop/view/icons/folder--exclamation.png
pictureTextCrop/view/icons/folder-bookmark.png
pictureTextCrop/view/icons/folder-broken.png
pictureTextCrop/view/icons/folder-export.png
pictureTextCrop/view/icons/folder-horizontal.png
pictureTextCrop/view/icons/folder.png
pictureTextCrop/view/icons/funnel--arrow.png
pictureTextCrop/view/icons/sticky-notes.png
pictureTextCrop/view/icons/toolbox.png
pictureTextCrop-0.6.1.dist-info/LICENSE
pictureTextCrop-0.6.1.dist-info/METADATA
pictureTextCrop-0.6.1.dist-info/WHEEL
pictureTextCrop-0.6.1.dist-info/top_level.txt
pictureTextCrop-0.6.1.dist-info/RECORD
