Metadata-Version: 2.1
Name: pictureTextCrop
Version: 0.6.1
Summary: Interactive extraction of selected text from images and batch processing of stored image files.
Author-email: Keith Watson <georgekeithwatson@gmail.com>
Maintainer-email: Keith Watson <keith.watson.py@gmail.com>
Project-URL: Homepage, https://github.com/keithCollins77093/PictureTextCrop
Keywords: image,text,extraction,text extraction,screenshot
Classifier: Programming Language :: Python :: 3.6
Classifier: License :: OSI Approved :: GNU Library or Lesser General Public License (LGPL)
Classifier: Operating System :: POSIX :: Linux
Classifier: Development Status :: 3 - Alpha
Classifier: Intended Audience :: Legal Industry
Classifier: Natural Language :: English
Classifier: Topic :: Multimedia :: Graphics :: Graphics Conversion
Classifier: Topic :: Office/Business
Requires-Python: >=3.6
License-File: LICENSE
Requires-Dist: Pillow
Requires-Dist: PyQt5
Requires-Dist: pytesseract
